[
  {
    "department": "대표",
    "name": "은종원"
  },
  {
    "department": "부사장",
    "name": "한기옥"
  },
  {
    "department": "운영본부장",
    "name": "이상윤"
  },
  {
    "department": "운영팀장",
    "name": "성창기"
  },
  {
    "department": "운영팀파트장",
    "name": "유영주"
  },
  {
    "department": "운영팀 공무공정파트",
    "name": "김진희"
  },
  {
    "department": "운영팀 공무공정파트",
    "name": "천춘학"
  },
  {
    "department": "운영팀 공무공정파트",
    "name": "김용만"
  },
  {
    "department": "운영팀 공무공정파트",
    "name": "허문기"
  },
  {
    "department": "운영팀 공무공정파트",
    "name": "조창규"
  },
  {
    "department": "운영팀 공무공정파트",
    "name": "최일영"
  },
  {
    "department": "운영팀 공무공정파트",
    "name": "임현규"
  },
  {
    "department": "운영팀 공무공정파트",
    "name": "황석영"
  },
  {
    "department": "운영팀 교대 A파트장",
    "name": "박도현"
  },
  {
    "department": "운영팀 교대 A파트",
    "name": "김상연"
  },
  {
    "department": "운영팀 교대 A파트",
    "name": "박선훈"
  },
  {
    "department": "운영팀 교대 A파트",
    "name": "박상진"
  },
  {
    "department": "운영팀 교대 A파트",
    "name": "최민준"
  },
  {
    "department": "운영팀 교대 B파트장",
    "name": "김세원"
  },
  {
    "department": "운영팀 교대 B파트",
    "name": "유관석"
  },
  {
    "department": "운영팀 교대 B파트",
    "name": "정재웅"
  },
  {
    "department": "운영팀 교대 B파트",
    "name": "이후성"
  },
  {
    "department": "운영팀 교대 B파트",
    "name": "김다은"
  },
  {
    "department": "운영팀 교대 C파트장",
    "name": "조형택"
  },
  {
    "department": "운영팀 교대 C파트",
    "name": "노연창"
  },
  {
    "department": "운영팀 교대 C파트",
    "name": "정준영"
  },
  {
    "department": "운영팀 교대 C파트",
    "name": "서진호"
  },
  {
    "department": "운영팀 교대 C파트",
    "name": "정우주"
  },
  {
    "department": "운영팀 교대 D파트장",
    "name": "김민태"
  },
  {
    "department": "운영팀 교대 D파트",
    "name": "이현우"
  },
  {
    "department": "운영팀 교대 D파트",
    "name": "고범곤"
  },
  {
    "department": "운영팀 교대 D파트",
    "name": "김상준"
  },
  {
    "department": "운영팀 교대 D파트",
    "name": "조우진"
  },
  {
    "department": "정비팀장",
    "name": "김삼태"
  },
  {
    "department": "정비팀 기계파트장",
    "name": "조계환"
  },
  {
    "department": "정비팀 기계파트",
    "name": "조인호"
  },
  {
    "department": "정비팀 기계파트",
    "name": "윤만수"
  },
  {
    "department": "정비팀 기계파트",
    "name": "박진모"
  },
  {
    "department": "정비팀 기계파트",
    "name": "이준민"
  },
  {
    "department": "정비팀 기계파트",
    "name": "이민준"
  },
  {
    "department": "정비팀 기계파트",
    "name": "안지원"
  },
  {
    "department": "정비팀 계전파트장",
    "name": "강동호"
  },
  {
    "department": "정비팀 계전파트",
    "name": "정빛남"
  },
  {
    "department": "정비팀 계전파트",
    "name": "김진환"
  },
  {
    "department": "정비팀 계전파트",
    "name": "전동훈"
  },
  {
    "department": "정비팀 계전파트",
    "name": "전민영"
  },
  {
    "department": "정비팀 계전파트",
    "name": "김동규"
  },
  {
    "department": "정비팀 계전파트",
    "name": "김우영"
  },
  {
    "department": "정비팀 계전파트",
    "name": "박상현"
  },
  {
    "department": "항만팀장",
    "name": "이병철"
  },
  {
    "department": "항만팀 DM파트장",
    "name": "유인철"
  },
  {
    "department": "항만팀 DM파트",
    "name": "여정수"
  },
  {
    "department": "항만팀 DM파트",
    "name": "어귀준"
  },
  {
    "department": "항만팀 DM파트",
    "name": "이규철"
  },
  {
    "department": "항만팀 DM파트",
    "name": "문영준"
  },
  {
    "department": "항만팀 실험실",
    "name": "김재식"
  },
  {
    "department": "항만팀 실험실",
    "name": "이기현"
  },
  {
    "department": "항만팀 실험실",
    "name": "김현"
  },
  {
    "department": "항만팀 실험실",
    "name": "강수훈"
  },
  {
    "department": "안전협력처장",
    "name": "양성모"
  },
  {
    "department": "안전환경팀장",
    "name": "손성원"
  },
  {
    "department": "안전환경팀 안전파트장",
    "name": "조옥동"
  },
  {
    "department": "안전환경팀 안전파트",
    "name": "박윤성"
  },
  {
    "department": "안전환경팀 안전파트",
    "name": "김성희"
  },
  {
    "department": "안전환경팀 보건환경파트장",
    "name": "나양우"
  },
  {
    "department": "안전환경팀 보건환경파트",
    "name": "송인주"
  },
  {
    "department": "안전환경팀 보건환경파트",
    "name": "김민우"
  },
  {
    "department": "안전환경팀 보건환경파트",
    "name": "최상이"
  },
  {
    "department": "대외협력팀장",
    "name": "백현선"
  },
  {
    "department": "대외협력팀 구매파트장",
    "name": "김경진"
  },
  {
    "department": "대외협력팀 구매파트",
    "name": "지원석"
  },
  {
    "department": "대외협력팀 구매파트",
    "name": "박미화"
  },
  {
    "department": "대외협력팀 구매파트",
    "name": "임성진"
  },
  {
    "department": "대외협력팀 구매파트",
    "name": "김의환"
  },
  {
    "department": "대외협력팀 CR파트장",
    "name": "유헌재"
  },
  {
    "department": "대외협력팀 CR파트",
    "name": "윤찬호"
  },
  {
    "department": "대외협력팀 CR파트",
    "name": "최민서"
  },
  {
    "department": "대외협력팀 CR파트",
    "name": "임지현"
  },
  {
    "department": "기술처장",
    "name": "심경대"
  },
  {
    "department": "기술혁신팀장",
    "name": "오호창"
  },
  {
    "department": "기술혁신팀",
    "name": "정승현"
  },
  {
    "department": "기술혁신팀",
    "name": "김인호"
  },
  {
    "department": "기술혁신팀",
    "name": "정재호"
  },
  {
    "department": "기술혁신팀",
    "name": "김지상"
  },
  {
    "department": "엔지니어링팀장",
    "name": "강동훈"
  },
  {
    "department": "엔지니어링팀",
    "name": "이영재"
  },
  {
    "department": "엔지니어링팀",
    "name": "이종영"
  },
  {
    "department": "엔지니어링팀",
    "name": "김홍식"
  },
  {
    "department": "사업본부장",
    "name": "정종선"
  },
  {
    "department": "사업본부 O/H",
    "name": "박재홍"
  },
  {
    "department": "사업기획팀장",
    "name": "이종우"
  },
  {
    "department": "사업기획팀",
    "name": "박송만"
  },
  {
    "department": "사업기획팀",
    "name": "한광석"
  },
  {
    "department": "사업기획팀",
    "name": "송유엽"
  },
  {
    "department": "사업기획팀",
    "name": "정수연"
  },
  {
    "department": "사업관리팀장",
    "name": "최광석"
  },
  {
    "department": "사업관리팀",
    "name": "이준구"
  },
  {
    "department": "사업관리팀",
    "name": "김다정"
  },
  {
    "department": "사업관리팀",
    "name": "안현진"
  },
  {
    "department": "경영지원본부장",
    "name": "이흥원"
  },
  {
    "department": "기획팀장",
    "name": "박순호"
  },
  {
    "department": "기획팀",
    "name": "인중협"
  },
  {
    "department": "기획팀",
    "name": "정동욱"
  },
  {
    "department": "기획팀",
    "name": "이민규"
  },
  {
    "department": "재무팀장",
    "name": "유정용"
  },
  {
    "department": "재무팀",
    "name": "정영준"
  },
  {
    "department": "재무팀",
    "name": "김해웅"
  },
  {
    "department": "재무팀",
    "name": "박동찬"
  },
  {
    "department": "재무팀",
    "name": "이휘연"
  },
  {
    "department": "재무팀",
    "name": "서청원"
  },
  {
    "department": "피플팀장",
    "name": "유재환"
  },
  {
    "department": "피플팀",
    "name": "손범구"
  },
  {
    "department": "피플팀",
    "name": "김세희"
  },
  {
    "department": "피플팀",
    "name": "장채윤"
  },
  {
    "department": "프로에스콤",
    "name": "박관용"
  },
  {
    "department": "서운",
    "name": "임충혁"
  },
  {
    "department": "하림",
    "name": "함희선"
  }
]
